setup.py
forecast_io/__init__.py
forecast_io.egg-info/PKG-INFO
forecast_io.egg-info/SOURCES.txt
forecast_io.egg-info/dependency_links.txt
forecast_io.egg-info/not-zip-safe
forecast_io.egg-info/requires.txt
forecast_io.egg-info/top_level.txt