Metadata-Version: 1.1
Name: forecast-io
Version: 0.1
Summary: forecast.io API wrapper in Python.
Home-page: https://github.com/kanski/forecast_io
Author: Bohdan Kanskyi
Author-email: kanskib@gmail.com
License: BSD
Keywords: forecast.io,api,wrapper
Platform: UNKNOWN
Classifier: Environment :: Web Environment
Classifier: Intended Audience :: Developers
Classifier: License :: OSI Approved :: BSD License
Classifier: Programming Language :: Python :: 2.7
Classifier: Topic :: Software Development :: Libraries :: Python Modules
